Ycolors/__init__.py
tsh_ycolors-0.5.0.dist-info/METADATA
tsh_ycolors-0.5.0.dist-info/WHEEL
tsh_ycolors-0.5.0.dist-info/top_level.txt
tsh_ycolors-0.5.0.dist-info/RECORD
