Metadata-Version: 2.4
Name: tsh-ycolors
Version: 0.5.0
Summary: A simple Python library for colored text printing.
Author-email: "T.S.H" <ysa31504@gmail.com>
License: MIT
Requires-Python: >=3.6
